skybaks/muffins/__init__.py
skybaks/muffins/bakery.py
skybaks/muffins/models/__init__.py
skybaks/muffins/models/muffin_model.py
pyplanet_muffins-1.2.1.dist-info/METADATA
pyplanet_muffins-1.2.1.dist-info/WHEEL
pyplanet_muffins-1.2.1.dist-info/RECORD
