Metadata-Version: 2.1
Name: pyplanet-muffins
Version: 1.2.1
Summary: A muffins plugin for the Pyplanet Trackmania Dedicated Server controller
Project-URL: Homepage, https://github.com/skybaks/pyplanet-muffins
Project-URL: Bug Tracker, https://github.com/skybaks/pyplanet-muffins/issues
Author-email: skybaks <tmflame@gmail.com>
Classifier: License :: OSI Approved :: GNU General Public License v3 (GPLv3)
Classifier: Operating System :: OS Independent
Classifier: Programming Language :: Python :: 3
Classifier: Programming Language :: Python :: 3 :: Only
Classifier: Topic :: Games/Entertainment
Requires-Python: >=3.7
